PicturesDedupeRename-1.0.5.data/scripts/dedupe-rename.py
PicturesDedupeRename-1.0.5.dist-info/DESCRIPTION.rst
PicturesDedupeRename-1.0.5.dist-info/METADATA
PicturesDedupeRename-1.0.5.dist-info/RECORD
PicturesDedupeRename-1.0.5.dist-info/WHEEL
PicturesDedupeRename-1.0.5.dist-info/metadata.json
PicturesDedupeRename-1.0.5.dist-info/top_level.txt
pictures/__init__.py
pictures/dedupe/__init__.py
pictures/dedupe/dedupe.py
pictures/rename/__init__.py
pictures/rename/rename.py
tests/__init__.py
tests/helpers.py
tests/test_dedupe.py
tests/test_rename.py
