Metadata-Version: 2.0
Name: PicturesDedupeRename
Version: 1.0.5
Summary: Dedupe a set of pictures in a given folder and rename them using the yyyymmdd_HHMMss format
Home-page: https://github.com/mina-asham/pictures-dedupe-and-rename
Author: Mina Asham
Author-email: mina.asham@hotmail.com
License: MIT
Platform: UNKNOWN
Requires-Dist: exifread
